airstuff/__init__.py
airstuff/air.py
airstuff/air_info.py
airstuff/app.py
airstuff/app_tkinter.py
airstuff/common.py
airstuff/driver_air.py
airstuff/dump_keyword.py
airstuff/example.py
airstuff/inspire.py
airstuff/journals.py
airstuff/old_parse_xml.py
airstuff/parse_inspire.py
airstuff/problem_gtk.py
airstuff/scopus.py
airstuff/test_parse_air.py
airstuff/workers.py
airstuff/wos.py
AirStuff-0.1.2.dist-info/METADATA
AirStuff-0.1.2.dist-info/WHEEL
AirStuff-0.1.2.dist-info/entry_points.txt
AirStuff-0.1.2.dist-info/top_level.txt
AirStuff-0.1.2.dist-info/RECORD
