Metadata-Version: 2.1
Name: AirStuff
Version: 0.1.2
Summary: Utilities to speedup AIR (Archivio Istituzionale della Ricerca) document upload, for HEP users
Home-page: https://github.com/wiso/airstuff
Author: Ruggero Turra
Author-email: ruggero.turra@cern.ch
License: UNKNOWN
Platform: UNKNOWN
Classifier: Programming Language :: Python :: 3
Classifier: Development Status :: 3 - Alpha
Classifier: Operating System :: OS Independent
Requires-Python: >=3.4
Requires-Dist: lxml
Requires-Dist: selenium
Requires-Dist: bibtexparser
Requires-Dist: requests
Requires-Dist: xmltodict
Requires-Dist: PyGObject
Requires-Dist: colorlog
Requires-Dist: colorama
